{
	"sn": "facebook",
	"custom": {},
	"lastEventDate": "13.02.2023 22:38 AQUECIMENTO (PAR)",
	"status": 2,
	"id": "100090003679798",
	"name": "",
	"amountFriends": "",
	"screenname": "Celina Gardel",
	"birthdate": "1986 July 16",
	"country": "Brazil",
	"isAvatarExists": false,
	"cookie": [
		{
			"domain": ".facebook.com",
			"expirationDate": 1710657423.100899,
			"hostOnly": false,
			"httpOnly": true,
			"name": "dbln",
			"path": "/login/device-based/",
			"sameSite": "no_restriction",
			"secure": true,
			"session": false,
			"storeId": "0",
			"value": "%7B%22100090003679798%22%3A%22VnxgVLW9%22%7D"
		},
		{
			"domain": ".facebook.com",
			"expirationDate": 1710657046.823017,
			"hostOnly": false,
			"httpOnly": true,
			"name": "sb",
			"path": "/",
			"sameSite": "no_restriction",
			"secure": true,
			"session": false,
			"storeId": "0",
			"value": "0zXnY20SGjAhbgVYjeoUsGn5"
		},
		{
			"domain": ".facebook.com",
			"expirationDate": 1710656981.221507,
			"hostOnly": false,
			"httpOnly": true,
			"name": "datr",
			"path": "/",
			"sameSite": "no_restriction",
			"secure": true,
			"session": false,
			"storeId": "0",
			"value": "0zXnY7XE37CWgE8y3lwTTS_h"
		},
		{
			"domain": ".facebook.com",
			"expirationDate": 1676701846.822948,
			"hostOnly": false,
			"httpOnly": false,
			"name": "locale",
			"path": "/",
			"sameSite": "no_restriction",
			"secure": true,
			"session": false,
			"storeId": "0",
			"value": "pt_BR"
		},
		{
			"domain": ".facebook.com",
			"expirationDate": 1707863474.523171,
			"hostOnly": false,
			"httpOnly": false,
			"name": "c_user",
			"path": "/",
			"sameSite": "no_restriction",
			"secure": true,
			"session": false,
			"storeId": "0",
			"value": "100090003679798"
		},
		{
			"domain": ".facebook.com",
			"expirationDate": 1707863474.523218,
			"hostOnly": false,
			"httpOnly": true,
			"name": "xs",
			"path": "/",
			"sameSite": "no_restriction",
			"secure": true,
			"session": false,
			"storeId": "0",
			"value": "14%3A2fvUc86ss9poGw%3A2%3A1676097045%3A-1%3A-1%3A%3AAcUk9NQaW0ztAcniqWy_7eYAwQTfuV2HTP3swq-PHA"
		},
		{
			"domain": ".facebook.com",
			"expirationDate": 1684103477.003407,
			"hostOnly": false,
			"httpOnly": true,
			"name": "fr",
			"path": "/",
			"sameSite": "no_restriction",
			"secure": true,
			"session": false,
			"storeId": "0",
			"value": "0Dh3M3XTrpiJREz7X.AWVim_U6XuRiR7bxWMlCcxNayGw.Bj6ro0.in.AAA.0.0.Bj6ro3.AWXEBTrveyA"
		},
		{
			"domain": ".facebook.com",
			"expirationDate": 1676932446,
			"hostOnly": false,
			"httpOnly": false,
			"name": "wd",
			"path": "/",
			"sameSite": "lax",
			"secure": true,
			"session": false,
			"storeId": "0",
			"value": "929x932"
		},
		{
			"domain": ".facebook.com",
			"hostOnly": false,
			"httpOnly": false,
			"name": "presence",
			"path": "/",
			"sameSite": "unspecified",
			"secure": true,
			"session": true,
			"storeId": "0",
			"value": "C%7B%22t3%22%3A%5B%5D%2C%22utc3%22%3A1676327643715%2C%22v%22%3A1%7D"
		}
	]
}