{
	"sn": "facebook",
	"custom": {},
	"lastEventDate": "24.01.2023 06:37 AQUECIMENTO (IMPAR)",
	"status": 2,
	"id": "100089240847814",
	"name": "",
	"amountFriends": "",
	"screenname": "Jandira Rosa",
	"birthdate": "1992 February 13",
	"country": "Brazil",
	"isAvatarExists": false,
	"cookie": [
		{
			"domain": ".facebook.com",
			"expirationDate": 1708952733.778295,
			"hostOnly": false,
			"httpOnly": true,
			"name": "dbln",
			"path": "/login/device-based/",
			"sameSite": "no_restriction",
			"secure": true,
			"session": false,
			"storeId": "0",
			"value": "%7B%22100089240847814%22%3A%22kmDGwgvq%22%7D"
		},
		{
			"domain": ".facebook.com",
			"expirationDate": 1708952397.170738,
			"hostOnly": false,
			"httpOnly": true,
			"name": "sb",
			"path": "/",
			"sameSite": "no_restriction",
			"secure": true,
			"session": false,
			"storeId": "0",
			"value": "-TLNY0CoMeQHHRmpe5WsahX8"
		},
		{
			"domain": ".facebook.com",
			"expirationDate": 1708952314.863814,
			"hostOnly": false,
			"httpOnly": true,
			"name": "datr",
			"path": "/",
			"sameSite": "no_restriction",
			"secure": true,
			"session": false,
			"storeId": "0",
			"value": "-TLNY8IlVPV1xL1CzOwCZSVg"
		},
		{
			"domain": ".facebook.com",
			"expirationDate": 1674997197.170682,
			"hostOnly": false,
			"httpOnly": false,
			"name": "locale",
			"path": "/",
			"sameSite": "no_restriction",
			"secure": true,
			"session": false,
			"storeId": "0",
			"value": "pt_BR"
		},
		{
			"domain": ".facebook.com",
			"expirationDate": 1706078068.501985,
			"hostOnly": false,
			"httpOnly": false,
			"name": "c_user",
			"path": "/",
			"sameSite": "no_restriction",
			"secure": true,
			"session": false,
			"storeId": "0",
			"value": "100089240847814"
		},
		{
			"domain": ".facebook.com",
			"expirationDate": 1706078068.502036,
			"hostOnly": false,
			"httpOnly": true,
			"name": "xs",
			"path": "/",
			"sameSite": "no_restriction",
			"secure": true,
			"session": false,
			"storeId": "0",
			"value": "11%3AhzWx6K5E6qyMEg%3A2%3A1674392396%3A-1%3A-1%3A%3AAcXncJbm8mra8MGurlcGKuMCHfT_0iMSAPJyhGZ_9Q"
		},
		{
			"domain": ".facebook.com",
			"expirationDate": 1682318075.35207,
			"hostOnly": false,
			"httpOnly": true,
			"name": "fr",
			"path": "/",
			"sameSite": "no_restriction",
			"secure": true,
			"session": false,
			"storeId": "0",
			"value": "05i0cnHTiAlO5Tqvk.AWWtF7L8W5jc_A4Il3aFisSNwjk.Bjz3v0.Id.AAA.0.0.Bjz3v7.AWVGiST2PXQ"
		},
		{
			"domain": ".facebook.com",
			"expirationDate": 1675146997,
			"hostOnly": false,
			"httpOnly": false,
			"name": "wd",
			"path": "/",
			"sameSite": "lax",
			"secure": true,
			"session": false,
			"storeId": "0",
			"value": "929x932"
		},
		{
			"domain": ".facebook.com",
			"hostOnly": false,
			"httpOnly": false,
			"name": "presence",
			"path": "/",
			"sameSite": "unspecified",
			"secure": true,
			"session": true,
			"storeId": "0",
			"value": "C%7B%22t3%22%3A%5B%5D%2C%22utc3%22%3A1674542195459%2C%22v%22%3A1%7D"
		}
	]
}